README.txt
setup.py
Products/__init__.py
Products.PageCacheManager.egg-info/PKG-INFO
Products.PageCacheManager.egg-info/SOURCES.txt
Products.PageCacheManager.egg-info/dependency_links.txt
Products.PageCacheManager.egg-info/entry_points.txt
Products.PageCacheManager.egg-info/namespace_packages.txt
Products.PageCacheManager.egg-info/not-zip-safe
Products.PageCacheManager.egg-info/requires.txt
Products.PageCacheManager.egg-info/top_level.txt
Products/PageCacheManager/AUTHORS.txt
Products/PageCacheManager/PageCache.py
Products/PageCacheManager/PageCacheManager.py
Products/PageCacheManager/__init__.py
Products/PageCacheManager/cache.gif
Products/PageCacheManager/interfaces.py
Products/PageCacheManager/version.txt
Products/PageCacheManager/www/addPCM.zpt
Products/PageCacheManager/www/editPCM.zpt
docs/HISTORY.txt
docs/INSTALL.txt
docs/LICENSE.txt
