Metadata-Version: 1.0
Name: Products.PageCacheManager
Version: 1.2
Summary: Cache rendered pages including headers
Home-page: http://svn.plone.org/svn/collective/Products.PageCacheManager
Author: Geoff Davis
Author-email: geoff@geoffdavis.net
License: ZPL
Keywords: caching zope CMF
Platform: UNKNOWN
Classifier: Framework :: Plone
Classifier: Programming Language :: Python
Classifier: Topic :: Software Development :: Libraries :: Python Modules
